{
    "@schema": "https://raw.githubusercontent.com/slicer/slicer/master/Modules/Loadable/Markups/Resources/Schema/markups-schema-v1.0.3.json#",
    "markups": [
        {
            "type": "ClosedCurve",
            "coordinateSystem": "LPS",
            "coordinateUnits": "mm",
            "locked": false,
            "fixedNumberOfControlPoints": false,
            "labelFormat": "%N-%d",
            "lastUsedControlPointNumber": 16,
            "controlPoints": [
                {
                    "id": "1",
                    "label": "CC_53-1",
                    "description": "",
                    "associatedNodeID": "vtkMRMLScalarVolumeNode19",
                    "position": [5.79224468920647, 52.87804403240435, -375.5956181406424],
                    "orientation": [-1.0, -0.0, -0.0, -0.0, -1.0, -0.0, 0.0, 0.0, 1.0],
                    "selected": true,
                    "locked": false,
                    "visibility": true,
                    "positionStatus": "defined"
                },
                {
                    "id": "2",
                    "label": "CC_53-2",
                    "description": "",
                    "associatedNodeID": "vtkMRMLScalarVolumeNode19",
                    "position": [7.8307516360719625, 52.91650636905665, -375.5956852701493],
                    "orientation": [-1.0, -0.0, -0.0, -0.0, -1.0, -0.0, 0.0, 0.0, 1.0],
                    "selected": true,
                    "locked": false,
                    "visibility": true,
                    "positionStatus": "defined"
                },
                {
                    "id": "3",
                    "label": "CC_53-3",
                    "description": "",
                    "associatedNodeID": "vtkMRMLScalarVolumeNode19",
                    "position": [9.369247445023234, 53.724215438552946, -375.59709498979413],
                    "orientation": [-1.0, -0.0, -0.0, -0.0, -1.0, -0.0, 0.0, 0.0, 1.0],
                    "selected": true,
                    "locked": false,
                    "visibility": true,
                    "positionStatus": "defined"
                },
                {
                    "id": "4",
                    "label": "CC_53-4",
                    "description": "",
                    "associatedNodeID": "vtkMRMLScalarVolumeNode19",
                    "position": [10.176957744717765, 55.147321894322815, -375.5995787815493],
                    "orientation": [-1.0, -0.0, -0.0, -0.0, -1.0, -0.0, 0.0, 0.0, 1.0],
                    "selected": true,
                    "locked": false,
                    "visibility": true,
                    "positionStatus": "defined"
                },
                {
                    "id": "5",
                    "label": "CC_53-5",
                    "description": "",
                    "associatedNodeID": "vtkMRMLScalarVolumeNode19",
                    "position": [10.023108163815085, 56.608890686730305, -375.6021297028114],
                    "orientation": [-1.0, -0.0, -0.0, -0.0, -1.0, -0.0, 0.0, 0.0, 1.0],
                    "selected": true,
                    "locked": false,
                    "visibility": true,
                    "positionStatus": "defined"
                },
                {
                    "id": "6",
                    "label": "CC_53-6",
                    "description": "",
                    "associatedNodeID": "vtkMRMLScalarVolumeNode19",
                    "position": [9.407709840227529, 57.72429844935463, -375.60407645851143],
                    "orientation": [-1.0, -0.0, -0.0, -0.0, -1.0, -0.0, 0.0, 0.0, 1.0],
                    "selected": true,
                    "locked": false,
                    "visibility": true,
                    "positionStatus": "defined"
                },
                {
                    "id": "7",
                    "label": "CC_53-7",
                    "description": "",
                    "associatedNodeID": "vtkMRMLScalarVolumeNode19",
                    "position": [8.523074750073938, 58.6089321921237, -375.60562043717005],
                    "orientation": [-1.0, -0.0, -0.0, -0.0, -1.0, -0.0, 0.0, 0.0, 1.0],
                    "selected": true,
                    "locked": false,
                    "visibility": true,
                    "positionStatus": "defined"
                },
                {
                    "id": "8",
                    "label": "CC_53-8",
                    "description": "",
                    "associatedNodeID": "vtkMRMLScalarVolumeNode19",
                    "position": [7.56151486947466, 59.070480231826856, -375.6064259912528],
                    "orientation": [-1.0, -0.0, -0.0, -0.0, -1.0, -0.0, 0.0, 0.0, 1.0],
                    "selected": true,
                    "locked": false,
                    "visibility": true,
                    "positionStatus": "defined"
                },
                {
                    "id": "9",
                    "label": "CC_53-9",
                    "description": "",
                    "associatedNodeID": "vtkMRMLScalarVolumeNode19",
                    "position": [6.176868641414011, 59.262791915031684, -375.60676163878725],
                    "orientation": [-1.0, -0.0, -0.0, -0.0, -1.0, -0.0, 0.0, 0.0, 1.0],
                    "selected": true,
                    "locked": false,
                    "visibility": true,
                    "positionStatus": "defined"
                },
                {
                    "id": "10",
                    "label": "CC_53-10",
                    "description": "",
                    "associatedNodeID": "vtkMRMLScalarVolumeNode19",
                    "position": [4.7922224133561855, 58.878168548601685, -375.6060903437183],
                    "orientation": [-1.0, -0.0, -0.0, -0.0, -1.0, -0.0, 0.0, 0.0, 1.0],
                    "selected": true,
                    "locked": false,
                    "visibility": true,
                    "positionStatus": "defined"
                },
                {
                    "id": "11",
                    "label": "CC_53-11",
                    "description": "",
                    "associatedNodeID": "vtkMRMLScalarVolumeNode19",
                    "position": [3.484500975748009, 58.10892181574884, -375.60474775358034],
                    "orientation": [-1.0, -0.0, -0.0, -0.0, -1.0, -0.0, 0.0, 0.0, 1.0],
                    "selected": true,
                    "locked": false,
                    "visibility": true,
                    "positionStatus": "defined"
                },
                {
                    "id": "12",
                    "label": "CC_53-12",
                    "description": "",
                    "associatedNodeID": "vtkMRMLScalarVolumeNode19",
                    "position": [2.3306291190374218, 56.91658937983121, -375.6026667388665],
                    "orientation": [-1.0, -0.0, -0.0, -0.0, -1.0, -0.0, 0.0, 0.0, 1.0],
                    "selected": true,
                    "locked": false,
                    "visibility": true,
                    "positionStatus": "defined"
                },
                {
                    "id": "13",
                    "label": "CC_53-13",
                    "description": "",
                    "associatedNodeID": "vtkMRMLScalarVolumeNode19",
                    "position": [2.176779538148118, 55.647332270633825, -375.6004514651389],
                    "orientation": [-1.0, -0.0, -0.0, -0.0, -1.0, -0.0, 0.0, 0.0, 1.0],
                    "selected": true,
                    "locked": false,
                    "visibility": true,
                    "positionStatus": "defined"
                },
                {
                    "id": "14",
                    "label": "CC_53-14",
                    "description": "",
                    "associatedNodeID": "vtkMRMLScalarVolumeNode19",
                    "position": [2.7921778617352935, 54.60884918129415, -375.5986389684527],
                    "orientation": [-1.0, -0.0, -0.0, -0.0, -1.0, -0.0, 0.0, 0.0, 1.0],
                    "selected": true,
                    "locked": false,
                    "visibility": true,
                    "positionStatus": "defined"
                },
                {
                    "id": "15",
                    "label": "CC_53-15",
                    "description": "",
                    "associatedNodeID": "vtkMRMLScalarVolumeNode19",
                    "position": [3.7152753471137068, 53.53190375531365, -375.5967593422596],
                    "orientation": [-1.0, -0.0, -0.0, -0.0, -1.0, -0.0, 0.0, 0.0, 1.0],
                    "selected": true,
                    "locked": false,
                    "visibility": true,
                    "positionStatus": "defined"
                },
                {
                    "id": "16",
                    "label": "CC_53-16",
                    "description": "",
                    "associatedNodeID": "vtkMRMLScalarVolumeNode19",
                    "position": [4.4845232515941476, 52.95496870568259, -375.59575239965613],
                    "orientation": [-1.0, -0.0, -0.0, -0.0, -1.0, -0.0, 0.0, 0.0, 1.0],
                    "selected": true,
                    "locked": false,
                    "visibility": true,
                    "positionStatus": "defined"
                }
            ],
            "measurements": [
                {
                    "name": "length",
                    "enabled": false,
                    "units": "mm",
                    "printFormat": "%-#4.4g%s"
                },
                {
                    "name": "curvature mean",
                    "enabled": false,
                    "printFormat": "%5.3f %s"
                },
                {
                    "name": "curvature max",
                    "enabled": false,
                    "printFormat": "%5.3f %s"
                },
                {
                    "name": "torsion mean",
                    "enabled": false,
                    "printFormat": "%5.3f %s"
                },
                {
                    "name": "torsion max",
                    "enabled": false,
                    "printFormat": "%5.3f %s"
                },
                {
                    "name": "area",
                    "enabled": false,
                    "units": "cm2",
                    "printFormat": "%-#4.4g%s"
                }
            ],
            "display": {
                "visibility": true,
                "opacity": 1.0,
                "color": [0.4, 1.0, 1.0],
                "selectedColor": [1.0, 0.5000076295109483, 0.5000076295109483],
                "activeColor": [0.4, 1.0, 0.0],
                "propertiesLabelVisibility": true,
                "pointLabelsVisibility": false,
                "textScale": 3.0,
                "glyphType": "Sphere3D",
                "glyphScale": 3.0,
                "glyphSize": 5.0,
                "useGlyphScale": true,
                "sliceProjection": false,
                "sliceProjectionUseFiducialColor": true,
                "sliceProjectionOutlinedBehindSlicePlane": false,
                "sliceProjectionColor": [1.0, 1.0, 1.0],
                "sliceProjectionOpacity": 0.6,
                "lineThickness": 0.2,
                "lineColorFadingStart": 1.0,
                "lineColorFadingEnd": 10.0,
                "lineColorFadingSaturation": 1.0,
                "lineColorFadingHueOffset": 0.0,
                "handlesInteractive": false,
                "translationHandleVisibility": true,
                "rotationHandleVisibility": true,
                "scaleHandleVisibility": true,
                "interactionHandleScale": 3.0,
                "snapMode": "toVisibleSurface"
            }
        }
    ]
}