{
    "@schema": "https://raw.githubusercontent.com/slicer/slicer/master/Modules/Loadable/Markups/Resources/Schema/markups-schema-v1.0.3.json#",
    "markups": [
        {
            "type": "ClosedCurve",
            "coordinateSystem": "LPS",
            "coordinateUnits": "mm",
            "locked": false,
            "fixedNumberOfControlPoints": false,
            "labelFormat": "%N-%d",
            "lastUsedControlPointNumber": 15,
            "controlPoints": [
                {
                    "id": "1",
                    "label": "CC_13-1",
                    "description": "",
                    "associatedNodeID": "vtkMRMLScalarVolumeNode19",
                    "position": [3.446038580537248, 55.27693198673012, -455.5999268411622],
                    "orientation": [-1.0, -0.0, -0.0, -0.0, -1.0, -0.0, 0.0, 0.0, 1.0],
                    "selected": true,
                    "locked": false,
                    "visibility": true,
                    "positionStatus": "defined"
                },
                {
                    "id": "2",
                    "label": "CC_13-2",
                    "description": "",
                    "associatedNodeID": "vtkMRMLScalarVolumeNode19",
                    "position": [4.292211275466766, 54.43076058060318, -455.59844999201044],
                    "orientation": [-1.0, -0.0, -0.0, -0.0, -1.0, -0.0, 0.0, 0.0, 1.0],
                    "selected": true,
                    "locked": false,
                    "visibility": true,
                    "positionStatus": "defined"
                },
                {
                    "id": "3",
                    "label": "CC_13-3",
                    "description": "",
                    "associatedNodeID": "vtkMRMLScalarVolumeNode19",
                    "position": [5.407620736960627, 54.161524224112384, -455.5979800854622],
                    "orientation": [-1.0, -0.0, -0.0, -0.0, -1.0, -0.0, 0.0, 0.0, 1.0],
                    "selected": true,
                    "locked": false,
                    "visibility": true,
                    "positionStatus": "defined"
                },
                {
                    "id": "4",
                    "label": "CC_13-4",
                    "description": "",
                    "associatedNodeID": "vtkMRMLScalarVolumeNode19",
                    "position": [6.638417384126885, 53.73843852105287, -455.5972416608863],
                    "orientation": [-1.0, -0.0, -0.0, -0.0, -1.0, -0.0, 0.0, 0.0, 1.0],
                    "selected": true,
                    "locked": false,
                    "visibility": true,
                    "positionStatus": "defined"
                },
                {
                    "id": "5",
                    "label": "CC_13-5",
                    "description": "",
                    "associatedNodeID": "vtkMRMLScalarVolumeNode19",
                    "position": [7.8307516360658695, 54.00767487755496, -455.5977115674346],
                    "orientation": [-1.0, -0.0, -0.0, -0.0, -1.0, -0.0, 0.0, 0.0, 1.0],
                    "selected": true,
                    "locked": false,
                    "visibility": true,
                    "positionStatus": "defined"
                },
                {
                    "id": "6",
                    "label": "CC_13-6",
                    "description": "",
                    "associatedNodeID": "vtkMRMLScalarVolumeNode19",
                    "position": [9.061548283226287, 54.776921610407435, -455.5990541575726],
                    "orientation": [-1.0, -0.0, -0.0, -0.0, -1.0, -0.0, 0.0, 0.0, 1.0],
                    "selected": true,
                    "locked": false,
                    "visibility": true,
                    "positionStatus": "defined"
                },
                {
                    "id": "7",
                    "label": "CC_13-7",
                    "description": "",
                    "associatedNodeID": "vtkMRMLScalarVolumeNode19",
                    "position": [9.446172235459631, 55.89232937303665, -455.60100091327257],
                    "orientation": [-1.0, -0.0, -0.0, -0.0, -1.0, -0.0, 0.0, 0.0, 1.0],
                    "selected": true,
                    "locked": false,
                    "visibility": true,
                    "positionStatus": "defined"
                },
                {
                    "id": "8",
                    "label": "CC_13-8",
                    "description": "",
                    "associatedNodeID": "vtkMRMLScalarVolumeNode19",
                    "position": [9.523097025899862, 57.43082283872991, -455.60368609354845],
                    "orientation": [-1.0, -0.0, -0.0, -0.0, -1.0, -0.0, 0.0, 0.0, 1.0],
                    "selected": true,
                    "locked": false,
                    "visibility": true,
                    "positionStatus": "defined"
                },
                {
                    "id": "9",
                    "label": "CC_13-9",
                    "description": "",
                    "associatedNodeID": "vtkMRMLScalarVolumeNode19",
                    "position": [8.907698702310988, 58.81546695785049, -455.60610275579677],
                    "orientation": [-1.0, -0.0, -0.0, -0.0, -1.0, -0.0, 0.0, 0.0, 1.0],
                    "selected": true,
                    "locked": false,
                    "visibility": true,
                    "positionStatus": "defined"
                },
                {
                    "id": "10",
                    "label": "CC_13-10",
                    "description": "",
                    "associatedNodeID": "vtkMRMLScalarVolumeNode19",
                    "position": [7.946138821712275, 59.16162798762668, -455.6067069213588],
                    "orientation": [-1.0, -0.0, -0.0, -0.0, -1.0, -0.0, 0.0, 0.0, 1.0],
                    "selected": true,
                    "locked": false,
                    "visibility": true,
                    "positionStatus": "defined"
                },
                {
                    "id": "11",
                    "label": "CC_13-11",
                    "description": "",
                    "associatedNodeID": "vtkMRMLScalarVolumeNode19",
                    "position": [6.407643012757042, 59.16162798761915, -455.6067069213588],
                    "orientation": [-1.0, -0.0, -0.0, -0.0, -1.0, -0.0, 0.0, 0.0, 1.0],
                    "selected": true,
                    "locked": false,
                    "visibility": true,
                    "positionStatus": "defined"
                },
                {
                    "id": "12",
                    "label": "CC_13-12",
                    "description": "",
                    "associatedNodeID": "vtkMRMLScalarVolumeNode19",
                    "position": [5.3306959464889445, 59.04624097768691, -455.60650553283807],
                    "orientation": [-1.0, -0.0, -0.0, -0.0, -1.0, -0.0, 0.0, 0.0, 1.0],
                    "selected": true,
                    "locked": false,
                    "visibility": true,
                    "positionStatus": "defined"
                },
                {
                    "id": "13",
                    "label": "CC_13-13",
                    "description": "",
                    "associatedNodeID": "vtkMRMLScalarVolumeNode19",
                    "position": [4.138361694551843, 58.392381254761595, -455.6053643312208],
                    "orientation": [-1.0, -0.0, -0.0, -0.0, -1.0, -0.0, 0.0, 0.0, 1.0],
                    "selected": true,
                    "locked": false,
                    "visibility": true,
                    "positionStatus": "defined"
                },
                {
                    "id": "14",
                    "label": "CC_13-14",
                    "description": "",
                    "associatedNodeID": "vtkMRMLScalarVolumeNode19",
                    "position": [3.369113790078373, 57.546209848626745, -455.6038874820691],
                    "orientation": [-1.0, -0.0, -0.0, -0.0, -1.0, -0.0, 0.0, 0.0, 1.0],
                    "selected": true,
                    "locked": false,
                    "visibility": true,
                    "positionStatus": "defined"
                },
                {
                    "id": "15",
                    "label": "CC_13-15",
                    "description": "",
                    "associatedNodeID": "vtkMRMLScalarVolumeNode19",
                    "position": [2.8306402569515754, 56.00771638293122, -455.6012023017932],
                    "orientation": [-1.0, -0.0, -0.0, -0.0, -1.0, -0.0, 0.0, 0.0, 1.0],
                    "selected": true,
                    "locked": false,
                    "visibility": true,
                    "positionStatus": "defined"
                }
            ],
            "measurements": [
                {
                    "name": "length",
                    "enabled": false,
                    "units": "mm",
                    "printFormat": "%-#4.4g%s"
                },
                {
                    "name": "curvature mean",
                    "enabled": false,
                    "printFormat": "%5.3f %s"
                },
                {
                    "name": "curvature max",
                    "enabled": false,
                    "printFormat": "%5.3f %s"
                },
                {
                    "name": "torsion mean",
                    "enabled": false,
                    "printFormat": "%5.3f %s"
                },
                {
                    "name": "torsion max",
                    "enabled": false,
                    "printFormat": "%5.3f %s"
                },
                {
                    "name": "area",
                    "enabled": false,
                    "units": "cm2",
                    "printFormat": "%-#4.4g%s"
                }
            ],
            "display": {
                "visibility": true,
                "opacity": 1.0,
                "color": [0.4, 1.0, 1.0],
                "selectedColor": [1.0, 0.5000076295109483, 0.5000076295109483],
                "activeColor": [0.4, 1.0, 0.0],
                "propertiesLabelVisibility": true,
                "pointLabelsVisibility": false,
                "textScale": 3.0,
                "glyphType": "Sphere3D",
                "glyphScale": 3.0,
                "glyphSize": 5.0,
                "useGlyphScale": true,
                "sliceProjection": false,
                "sliceProjectionUseFiducialColor": true,
                "sliceProjectionOutlinedBehindSlicePlane": false,
                "sliceProjectionColor": [1.0, 1.0, 1.0],
                "sliceProjectionOpacity": 0.6,
                "lineThickness": 0.2,
                "lineColorFadingStart": 1.0,
                "lineColorFadingEnd": 10.0,
                "lineColorFadingSaturation": 1.0,
                "lineColorFadingHueOffset": 0.0,
                "handlesInteractive": false,
                "translationHandleVisibility": true,
                "rotationHandleVisibility": true,
                "scaleHandleVisibility": true,
                "interactionHandleScale": 3.0,
                "snapMode": "toVisibleSurface"
            }
        }
    ]
}